cutadapt/__init__.py
cutadapt/__main__.py
cutadapt/_align.cp311-win_amd64.pyd
cutadapt/_align.pyi
cutadapt/_kmer_finder.cp311-win_amd64.pyd
cutadapt/_kmer_finder.pyi
cutadapt/_match_tables.py
cutadapt/_version.py
cutadapt/adapters.py
cutadapt/align.py
cutadapt/cli.py
cutadapt/files.py
cutadapt/info.cp311-win_amd64.pyd
cutadapt/info.pyi
cutadapt/json.py
cutadapt/kmer_heuristic.py
cutadapt/log.py
cutadapt/modifiers.py
cutadapt/parser.py
cutadapt/pipeline.py
cutadapt/predicates.py
cutadapt/qualtrim.cp311-win_amd64.pyd
cutadapt/qualtrim.pyi
cutadapt/report.py
cutadapt/runners.py
cutadapt/statistics.py
cutadapt/steps.py
cutadapt/tokenizer.py
cutadapt/utils.py
cutadapt-5.2.dist-info/licenses/LICENSE
cutadapt-5.2.dist-info/METADATA
cutadapt-5.2.dist-info/WHEEL
cutadapt-5.2.dist-info/entry_points.txt
cutadapt-5.2.dist-info/top_level.txt
cutadapt-5.2.dist-info/RECORD
