Metadata-Version: 2.4
Name: cutadapt
Version: 5.2
Summary: Adapter trimming and other preprocessing of high-throughput sequencing reads
Author-email: Marcel Martin <marcel.martin@scilifelab.se>
License-Expression: MIT
Project-URL: Homepage, https://cutadapt.readthedocs.io/
Project-URL: Changelog, https://cutadapt.readthedocs.io/en/stable/changes.html
Project-URL: Repository, https://github.com/marcelm/cutadapt/
Classifier: Development Status :: 5 - Production/Stable
Classifier: Environment :: Console
Classifier: Intended Audience :: Science/Research
Classifier: Programming Language :: Cython
Classifier: Programming Language :: Python :: 3
Classifier: Topic :: Scientific/Engineering :: Bio-Informatics
Requires-Python: >=3.9
License-File: LICENSE
Requires-Dist: dnaio>=1.2.3
Requires-Dist: xopen>=1.6.0
Provides-Extra: dev
Requires-Dist: Cython; extra == "dev"
Requires-Dist: pytest; extra == "dev"
Requires-Dist: pytest-timeout; extra == "dev"
Requires-Dist: pytest-mock; extra == "dev"
Requires-Dist: sphinx; extra == "dev"
Requires-Dist: sphinx_issues; extra == "dev"
Requires-Dist: sphinx_better_subsection; extra == "dev"
Dynamic: license-file
